sequenz/__init__.py
sequenz-0.0.1.dist-info/LICENSE
sequenz-0.0.1.dist-info/METADATA
sequenz-0.0.1.dist-info/WHEEL
sequenz-0.0.1.dist-info/top_level.txt
sequenz-0.0.1.dist-info/RECORD
